[{"categories":["Clothing"],"contents":"","permalink":"/blog/depop/","tags":["Clothes","Resale","Lowest Fees!"],"title":""},{"categories":["Clothing"],"contents":"","permalink":"/blog/mercari/","tags":["Clothes","Resale"],"title":""},{"categories":["Clothing"],"contents":"","permalink":"/blog/poshmark/","tags":["Clothes","Resale","Favorite"],"title":""},{"categories":null,"contents":"Welcome to my clothing shop! I primarily sell vintage and modern clothes, but have a bit of everything. I currently sell through Poshmark, Mercari, and Depop - you can visit those below. Tap on any of the tiles below to go to the respective site. My entire closet is on each platform, so pick your favorite!\n","permalink":"/blog/welcome/","tags":null,"title":"Welcome!"}]